mlflow_for_ml_dev/__init__.py
mlflow_for_ml_dev/entrypoints/start_tutorial.py
mlflow_for_ml_dev/experiments/custom_models.py
mlflow_for_ml_dev/experiments/exp_utils.py
mlflow_for_ml_dev/notebooks/exploration.ipynb
mlflow_for_ml_dev/notebooks/images/mlflow_run.jpeg
mlflow_for_ml_dev/notebooks/images/text_file.txt
mlflow_for_ml_dev/notebooks/mlflow_tracking/1_experiments/1_main_concepts.ipynb
mlflow_for_ml_dev/notebooks/mlflow_tracking/1_experiments/2_create_experiment.ipynb
mlflow_for_ml_dev/notebooks/mlflow_tracking/1_experiments/3_retrieve_experiments.ipynb
mlflow_for_ml_dev/notebooks/mlflow_tracking/1_experiments/4_update_experiment.ipynb
mlflow_for_ml_dev/notebooks/mlflow_tracking/1_experiments/5_delete_experiment.ipynb
mlflow_for_ml_dev/notebooks/mlflow_tracking/2_runs/1_create_run.ipynb
mlflow_for_ml_dev/notebooks/mlflow_tracking/2_runs/2_logging_functions.ipynb
mlflow_for_ml_dev/notebooks/mlflow_tracking/2_runs/3_example.ipynb
mlflow_for_ml_dev/notebooks/mlflow_tracking/2_runs/4_logging_models.ipynb
mlflow_for_ml_dev/notebooks/mlflow_tracking/2_runs/5_mlflow_autologing.ipynb
mlflow_for_ml_dev/notebooks/mlflow_tracking/2_runs/artifacts_example/feature_importance.png
mlflow_for_ml_dev/notebooks/mlflow_tracking/2_runs/artifacts_example/predictions.csv
mlflow_for_ml_dev/notebooks/mlflow_tracking/2_runs/artifacts_example/rf_5trees.png
mlflow_for_ml_dev/notebooks/mlflow_tracking/3_custom_functions/1_custom_functions.ipynb
mlflow_for_ml_dev/notebooks/mlflow_tracking/3_custom_functions/2_custom_function_model_drift_usecase.ipynb
mlflow_for_ml_dev/notebooks/mlflow_tracking/3_custom_functions/3_custom_function_wrapping_multiple_models.ipynb
mlflow_for_ml_dev/notebooks/mlflow_tracking/3_custom_functions/training_data.csv
mlflow_for_ml_dev/notebooks/model_registry/1_registering_a_model.ipynb
mlflow_for_ml_dev/notebooks/model_registry/2_registering_a_model.ipynb
mlflow_for_ml_dev/notebooks/model_registry/3_registering_a_model.ipynb
mlflow_for_ml_dev-0.1.4.dist-info/entry_points.txt
mlflow_for_ml_dev-0.1.4.dist-info/METADATA
mlflow_for_ml_dev-0.1.4.dist-info/WHEEL
mlflow_for_ml_dev-0.1.4.dist-info/RECORD
